log_redactor/__init__.py
log_redactor/formatters.py
log_redactor-0.1.1.dist-info/AUTHORS.rst
log_redactor-0.1.1.dist-info/LICENSE
log_redactor-0.1.1.dist-info/METADATA
log_redactor-0.1.1.dist-info/WHEEL
log_redactor-0.1.1.dist-info/top_level.txt
log_redactor-0.1.1.dist-info/RECORD
