Metadata-Version: 2.1
Name: log-redactor
Version: 0.1.1
Summary: Remove a pattern from your logs
Home-page: https://github.com/reedrichards-python/log_redactor
Author: Robert Wendt
Author-email: rwendt1337@gmail.com
License: MIT license
Keywords: log_redactor
Platform: UNKNOWN
Classifier: Development Status :: 2 - Pre-Alpha
Classifier: Intended Audience :: Developers
Classifier: License :: OSI Approved :: MIT License
Classifier: Natural Language :: English
Classifier: Programming Language :: Python :: 3
Classifier: Programming Language :: Python :: 3.6
Classifier: Programming Language :: Python :: 3.7
